snapmark/__init__.py
snapmark/core.py
snapmark/shortcuts.py
snapmark/checking/__init__.py
snapmark/checking/checking.py
snapmark/entities/__init__.py
snapmark/entities/add_entities.py
snapmark/mark_algorithm/__init__.py
snapmark/mark_algorithm/mark_algorithm.py
snapmark/operations/__init__.py
snapmark/operations/aligner.py
snapmark/operations/basic_operations.py
snapmark/operations/counter.py
snapmark/sequence/__init__.py
snapmark/sequence/sequence_legacy.py
snapmark/sequence/sequence_system.py
snapmark/utils/__init__.py
snapmark/utils/backup_manager.py
snapmark/utils/helpers.py
snapmark/utils/messages.py
snapmark/utils/segments_dict.py
snapmark-2.0.5.dist-info/licenses/LICENSE
snapmark-2.0.5.dist-info/METADATA
snapmark-2.0.5.dist-info/WHEEL
snapmark-2.0.5.dist-info/top_level.txt
snapmark-2.0.5.dist-info/RECORD
