Metadata-Version: 2.4
Name: snapmark
Version: 2.0.5
Summary: Python library for automated DXF file marking and manipulation to engrave your cut files
Author: Federico Sidraschi
License: MIT
Project-URL: Homepage, https://github.com/serg-you-lin/SnapMark
Project-URL: Repository, https://github.com/serg-you-lin/SnapMark
Project-URL: Documentation, https://github.com/serg-you-lin/SnapMark#readme
Project-URL: Issues, https://github.com/serg-you-lin/SnapMark/issues
Keywords: dxf,autocad,cad,marking,automation,batch-processing,manufacturing,cnc,cam,drawing,ezdxf,design-automation,dxf-files,cad-automation,technical-drawing,mechanical-design
Classifier: Development Status :: 4 - Beta
Classifier: Intended Audience :: Developers
Classifier: Intended Audience :: Manufacturing
Classifier: Topic :: Software Development :: Libraries :: Python Modules
Classifier: Topic :: Scientific/Engineering
Classifier: Topic :: Office/Business
Classifier: License :: OSI Approved :: MIT License
Classifier: Programming Language :: Python :: 3
Classifier: Programming Language :: Python :: 3.8
Classifier: Programming Language :: Python :: 3.9
Classifier: Programming Language :: Python :: 3.10
Classifier: Programming Language :: Python :: 3.11
Classifier: Programming Language :: Python :: 3.12
Classifier: Operating System :: OS Independent
Requires-Python: >=3.8
License-File: LICENSE
Requires-Dist: ezdxf>=1.0.0
Dynamic: license-file
